[
    {
        "id": 1,
        "nombre": "Nike Revolution 6",
        "talles": [
            40,
            41,
            42
        ],
        "color": "Negro",
        "descripcion": "Priorizamos la comodidad, especialmente para nuestros atletas que crecen en movimiento. Confeccionado con un 20% de contenido reciclado por peso y un diseño ligero y transpirable, los niños pueden llevar el Nike Revolution 6 durante todo el día para usarlo en cualquier momento con cualquier atuendo. Las correas y las agujetas elásticas hacen que sea muy fácil de poner. El arte y el atletismo. Esta edición especial inspira a los niños a dibujar y expresarse a través del arte. El increíble estampado Nike es como sus libros de pintar favoritos. Nos encantaría verlos crear su propio arte. Comodidad y frescura La tela ligera proporciona transpirabilidad para que los pies pequeños mantengan la frescura.",
        "precio": "110.000",
        "imagen": "nike8.webp",
        "category": "destacado"
    },
    {
        "id": 2,
        "nombre": "Nike Revolution 6",
        "talles": [
            40,
            41
        ],
        "color": "Rosado",
        "descripcion": "zapatillas nike ultimo modelo 2023",
        "precio": "110.000",
        "imagen": "nike6.webp",
        "category": "destacado"
    },
    {
        "id": 3,
        "nombre": "Nike Air Max",
        "talles": [
            38
        ],
        "color": "Negro",
        "descripcion": "zapatillas nike ultimo modelo 2023",
        "precio": "90.000",
        "imagen": "nike5.webp",
        "category": "destacado"
    },
    {
        "id": 4,
        "nombre": "Nike Zoom",
        "talles": [
            39,
            40,
            41
        ],
        "color": "Azul",
        "descripcion": "zapatillas nike ultimo modelo 2023",
        "precio": "75.000",
        "imagen": "nike6.webp",
        "category": "destacado"
    },
    {
        "id": 5,
        "nombre": "Nike Revolution 6",
        "talles": [
            39,
            42,
            43
        ],
        "color": "varios colores para elegir",
        "descripcion": "zapatillas nike ultimo modelo 2023",
        "precio": "110.000",
        "imagen": "nike7.webp",
        "category": "oferta"
    },
    {
        "id": 6,
        "nombre": "Nike Air Max",
        "talles": [
            38,
            40
        ],
        "color": "Negro",
        "descripcion": "zapatillas nike ultimo modelo 2023",
        "precio": "90.000",
        "imagen": "nike8.webp",
        "category": "oferta"
    },
    {
        "id": 7,
        "nombre": "Nike Revolution 6",
        "talles": [
            38,
            40,
            42
        ],
        "color": "varios colores para elegir",
        "descripcion": "zapatillas nike ultimo modelo 2023",
        "precio": "110.000",
        "imagen": "nike5.webp",
        "category": "oferta"
    },
    {
        "id": 9,
        "nombre": "Nike Air Max",
        "talles": [
            38,
            39
        ],
        "color": "Negro",
        "descripcion": "zapatillas nike ultimo modelo 2023",
        "precio": "90.000",
        "imagen": "nike6.webp",
        "category": "oferta"
    },
    {
        "id": 9,
        "nombre": "Nike Air Max",
        "talles": [
            38,
            39
        ],
        "color": "Negro",
        "descripcion": "zapatillas nike ultimo modelo 2023",
        "precio": "90.000",
        "imagen": "nike6.webp",
        "category": "destacado"
    },
    {
        "id": 10,
        "nombre": "Nike Revolution 6",
        "talles": [
            40,
            41,
            42
        ],
        "color": "Negro",
        "descripcion": "zapatillas nike ultimo modelo 2023",
        "precio": "110.000",
        "imagen": "nike8.webp",
        "category": "lanzamiento"
    },
    {
        "id": 11,
        "nombre": "Nike Revolution 6",
        "talles": [
            40,
            41
        ],
        "color": "Rosado",
        "descripcion": "zapatillas nike ultimo modelo 2023",
        "precio": "110.000",
        "imagen": "nike6.webp",
        "category": "destacado"
    },
    {
        "id": 12,
        "nombre": "Nike Air Max",
        "talles": [
            38
        ],
        "color": "Negro",
        "descripcion": "zapatillas nike ultimo modelo 2023",
        "precio": "90.000",
        "imagen": "nike5.webp",
        "category": "lanzamiento"
    },
    {
        "id": 13,
        "nombre": "Nike Zoom",
        "talles": [
            39,
            40,
            41
        ],
        "color": "Azul",
        "descripcion": "zapatillas nike ultimo modelo 2023",
        "precio": "75.000",
        "imagen": "nike6.webp",
        "category": "destacado"
    },
    {
        "id": 14,
        "nombre": "Nike Revolution 6",
        "talles": [
            39,
            42,
            43
        ],
        "color": "varios colores para elegir",
        "descripcion": "zapatillas nike ultimo modelo 2023",
        "precio": "110.000",
        "imagen": "nike7.webp",
        "category": "lanzamiento"
    },
    {
        "id": 15,
        "nombre": "Nike Air Max",
        "talles": [
            38,
            40
        ],
        "color": "Negro",
        "descripcion": "zapatillas nike ultimo modelo 2023",
        "precio": "90.000",
        "imagen": "nike8.webp",
        "category": "oferta"
    },
    {
        "id": 16,
        "nombre": "Nike Revolution 6",
        "talles": [
            38,
            40,
            42
        ],
        "color": "varios colores para elegir",
        "descripcion": "zapatillas nike ultimo modelo 2023",
        "precio": "110.000",
        "imagen": "nike5.webp",
        "category": "oferta"
    },
    {
        "id": 17,
        "nombre": "Nike Air Max",
        "talles": [
            38,
            39
        ],
        "color": "Negro",
        "descripcion": "zapatillas nike ultimo modelo 2023",
        "precio": "90.000",
        "imagen": "nike6.webp",
        "category": "oferta"
    },
    {
        "id": 18,
        "nombre": "Nike Air Max",
        "talles": [
            38,
            39
        ],
        "color": "Negro",
        "descripcion": "zapatillas nike ultimo modelo 2023",
        "precio": "90.000",
        "imagen": "nike6.webp",
        "category": "lanzamiento"
    }
]